virapi_cli.py
virapi_cli-0.1.0.dist-info/METADATA
virapi_cli-0.1.0.dist-info/WHEEL
virapi_cli-0.1.0.dist-info/entry_points.txt
virapi_cli-0.1.0.dist-info/top_level.txt
virapi_cli-0.1.0.dist-info/RECORD
