Metadata-Version: 2.4
Name: virapi-cli
Version: 0.1.0
Summary: Command Line Interface (CLI) for the virapi ASGI framework.
Author-email: Víctor Gómez <mdsuanzes@gmail.com>
License-Expression: MIT
Requires-Python: >=3.9
Requires-Dist: virapi
Requires-Dist: uvicorn>=0.20.0
